llm_dialog_manager/__init__.py
llm_dialog_manager/agent.py
llm_dialog_manager/chat_history.py
llm_dialog_manager/key_manager.py
llm_dialog_manager/clients/__init__.py
llm_dialog_manager/clients/anthropic_client.py
llm_dialog_manager/clients/base.py
llm_dialog_manager/clients/gemini_client.py
llm_dialog_manager/clients/openai_client.py
llm_dialog_manager/clients/x_client.py
llm_dialog_manager/formatters/__init__.py
llm_dialog_manager/formatters/anthropic.py
llm_dialog_manager/formatters/base.py
llm_dialog_manager/formatters/gemini.py
llm_dialog_manager/formatters/openai.py
llm_dialog_manager/formatters/x.py
llm_dialog_manager/utils/__init__.py
llm_dialog_manager/utils/environment.py
llm_dialog_manager/utils/image_tools.py
llm_dialog_manager/utils/logging.py
llm_dialog_manager-0.5.3.dist-info/licenses/LICENSE
llm_dialog_manager-0.5.3.dist-info/METADATA
llm_dialog_manager-0.5.3.dist-info/WHEEL
llm_dialog_manager-0.5.3.dist-info/top_level.txt
llm_dialog_manager-0.5.3.dist-info/RECORD
